reaction_path_step/__init__.py
reaction_path_step/_version.py
reaction_path_step/metadata.py
reaction_path_step/reaction_path.py
reaction_path_step/reaction_path_parameters.py
reaction_path_step/reaction_path_step.py
reaction_path_step/tk_reaction_path.py
reaction_path_step/data/properties.csv
reaction_path_step/data/references.bib
reaction_path_step-2024.12.14.dist-info/AUTHORS.rst
reaction_path_step-2024.12.14.dist-info/LICENSE
reaction_path_step-2024.12.14.dist-info/METADATA
reaction_path_step-2024.12.14.dist-info/WHEEL
reaction_path_step-2024.12.14.dist-info/entry_points.txt
reaction_path_step-2024.12.14.dist-info/top_level.txt
reaction_path_step-2024.12.14.dist-info/zip-safe
reaction_path_step-2024.12.14.dist-info/RECORD
