Metadata-Version: 2.1
Name: reaction_path_step
Version: 2024.12.14
Summary: A SEAMM plugin for finding transition states and reaction paths
Home-page: https://github.com/molssi-seamm/reaction_path_step
Author: Paul Saxe
Author-email: psaxe@molssi.org
License: BSD-3-Clause
Keywords: SEAMM,SEAMMplugin,flowchart
Platform: Linux
Platform: Mac OS-X
Platform: Unix
Platform: Windows
Classifier: Environment :: Plugins
Classifier: Development Status :: 2 - Pre-Alpha
Classifier: Intended Audience :: Science/Research
Classifier: Topic :: Scientific/Engineering :: Chemistry
Classifier: Topic :: Scientific/Engineering :: Physics
Classifier: License :: OSI Approved :: BSD License
Classifier: Natural Language :: English
Classifier: Programming Language :: Python :: 3 :: Only
Classifier: Programming Language :: Python :: 3.8
Classifier: Programming Language :: Python :: 3.9
License-File: LICENSE
License-File: AUTHORS.rst
Requires-Dist: ase
Requires-Dist: molsystem
Requires-Dist: numpy
Requires-Dist: read-structure-step
Requires-Dist: seamm
Requires-Dist: seamm-ase
Requires-Dist: seamm-util
Requires-Dist: seamm-widgets
Requires-Dist: tabulate
